README.md
pyproject.toml
setup.cfg
setup.py
spidex/__init__.py
spidex/constants.py
spidex/error.py
spidex/request_client.py
spidex/api/__init__.py
spidex/api/private.py
spidex/api/public.py
spidex/eth_sign/__init__.py
spidex/eth_sign/eip712struct_entity.py
spidex/eth_sign/signers.py
spidex/eth_sign/eip712_structs/__init__.py
spidex/eth_sign/eip712_structs/domain_separator.py
spidex/eth_sign/eip712_structs/struct.py
spidex/eth_sign/eip712_structs/types.py
spidex/lib/__init__.py
spidex/lib/utils.py
spidex_python_sdk.egg-info/PKG-INFO
spidex_python_sdk.egg-info/SOURCES.txt
spidex_python_sdk.egg-info/dependency_links.txt
spidex_python_sdk.egg-info/requires.txt
spidex_python_sdk.egg-info/top_level.txt
spidex_python_sdk.egg-info/zip-safe